LICENSE
README.md
setup.cfg
setup.py
premierleaguedata/__init__.py
premierleaguedata/api.py
premierleaguedata.egg-info/PKG-INFO
premierleaguedata.egg-info/SOURCES.txt
premierleaguedata.egg-info/dependency_links.txt
premierleaguedata.egg-info/requires.txt
premierleaguedata.egg-info/top_level.txt